aimbat/__init__.py
aimbat/cli.py
aimbat/commands/checkdata.py
aimbat/commands/defaults.py
aimbat/commands/sampledata.py
aimbat/lib/defaults.py
aimbat/lib/defaults.yml
aimbat-0.0.0.dev0.dist-info/METADATA
aimbat-0.0.0.dev0.dist-info/WHEEL
aimbat-0.0.0.dev0.dist-info/entry_points.txt
aimbat-0.0.0.dev0.dist-info/RECORD
