Metadata-Version: 2.1
Name: aimbat
Version: 0.0.0.dev0
Summary: AIMBAT: Automated and Interactive Measurement of Body-wave Arrival Times.
License: GPL-3.0-or-later
Author: Xiaoting Lou
Author-email: xlou@u.northwestern.edu
Requires-Python: >=3.10,<3.12
Classifier: Development Status :: 5 - Production/Stable
Classifier: Intended Audience :: Science/Research
Classifier: License :: OSI Approved :: GNU General Public License v3 or later (GPLv3+)
Classifier: Operating System :: OS Independent
Classifier: Programming Language :: Python :: 3
Classifier: Programming Language :: Python :: 3.10
Classifier: Programming Language :: Python :: 3.11
Classifier: Topic :: Scientific/Engineering
Requires-Dist: click (>=8.1.7,<9.0.0)
Requires-Dist: prettytable (>=3.8.0,<4.0.0)
Requires-Dist: pysmo (>=1.0.0-dev0,<2.0.0)
Project-URL: Documentation, https://pysmo.readthedocs.io
